README.md
setup.py
ethereum_input_decoder/__init__.py
ethereum_input_decoder/__main__.py
ethereum_input_decoder/decoder.py
ethereum_input_decoder.egg-info/PKG-INFO
ethereum_input_decoder.egg-info/SOURCES.txt
ethereum_input_decoder.egg-info/dependency_links.txt
ethereum_input_decoder.egg-info/requires.txt
ethereum_input_decoder.egg-info/top_level.txt