Metadata-Version: 1.1
Name: ethereum-input-decoder
Version: 0.1
Summary: Decode transaction inputs based on the contract ABI
Home-page: https://github.com/tintinweb/ethereum-input-decoder/
Author: tintinweb
Author-email: tintinweb@oststrom.com
License: GPLv3
Download-URL: https://github.com/tintinweb/ethereum-input-decoder/tarball/v0.1
Keywords: ethereum,blockchain,input,transaction,decoder
Platform: UNKNOWN
